setup.py
calchas.egg-info/PKG-INFO
calchas.egg-info/SOURCES.txt
calchas.egg-info/dependency_links.txt
calchas.egg-info/requires.txt
calchas.egg-info/top_level.txt
calchas_datamodel/__init__.py
calchas_datamodel/abstractExpression.py
calchas_datamodel/abstractLiteralExpression.py
calchas_datamodel/autoEnum.py
calchas_datamodel/constantExpression.py
calchas_datamodel/dictFunctionExpression.py
calchas_datamodel/dummy.py
calchas_datamodel/floatLiteralExpression.py
calchas_datamodel/formulaFunctionExpression.py
calchas_datamodel/functionCallExpression.py
calchas_datamodel/functionExpression.py
calchas_datamodel/idExpression.py
calchas_datamodel/integerLiteralCalchasExpression.py
calchas_datamodel/pattern.py
calchas_datamodel/placeholder.py
calchas_datamodel/rewriting.py
calchas_datamodel/visitor.py
calchas_polyparser/__init__.py
calchas_polyparser/isMath.py
calchas_polyparser/latexLex.py
calchas_polyparser/latexPreprocessing.py
calchas_polyparser/latexTranslate.py
calchas_polyparser/latexYacc.py
calchas_polyparser/mathematicaLex.py
calchas_polyparser/mathematicaTranslate.py
calchas_polyparser/mathematicaYacc.py
calchas_polyparser/naturalLex.py
calchas_polyparser/naturalPreprocessing.py
calchas_polyparser/naturalTranslate.py
calchas_polyparser/naturalYacc.py
calchas_polyprinter/__init__.py
calchas_polyprinter/abstract_printer.py
calchas_polyprinter/default_printer.py
calchas_sympy/__init__.py
calchas_sympy/sympyFunctions.py
calchas_sympy/translator.py
calchas_transformations/__init__.py
calchas_transformations/lambdafier.py
calchas_transformations/simplify_prod.py
calchas_transformations/simplify_sum.py
calchas_transformations/transformation.py
calchas_transformations/transformer.py